extract_iocs/__init__.py
extract_iocs/extract_iocs.py
extract_iocs-1.0.0.dist-info/DESCRIPTION.rst
extract_iocs-1.0.0.dist-info/METADATA
extract_iocs-1.0.0.dist-info/metadata.json
extract_iocs-1.0.0.dist-info/RECORD
extract_iocs-1.0.0.dist-info/top_level.txt
extract_iocs-1.0.0.dist-info/WHEEL
