Metadata-Version: 2.0
Name: extract-iocs
Version: 1.0.0
Summary: Extracts indicators of compromise (IOCs), including domain names, IPv4 addresses, email addresses, and hashes, from text.
Home-page: https://github.com/mosesschwartz/extract_iocs
Author: Moses Schwartz, Bechtel CIRT
Author-email: moses.schwartz@gmail.com
License: MIT
Keywords: security ioc domain email hash md5 sha1 sha256 regex
Platform: UNKNOWN
Classifier: Development Status :: 3 - Alpha
Classifier: Intended Audience :: Developers
Classifier: Topic :: Software Development
Classifier: Topic :: Utilities
Classifier: License :: OSI Approved :: MIT License
Classifier: Programming Language :: Python :: 2
Classifier: Programming Language :: Python :: 2.7
Requires-Dist: stix
Requires-Dist: cybox
Provides-Extra: test
Provides-Extra: dev
